JINTFP/__init__.py
JINTFP/_node.py
JINTFP/my_patterns.py
JINTFP-0.1.1.dist-info/LICENSE
JINTFP-0.1.1.dist-info/METADATA
JINTFP-0.1.1.dist-info/WHEEL
JINTFP-0.1.1.dist-info/top_level.txt
JINTFP-0.1.1.dist-info/RECORD
