Metadata-Version: 2.1
Name: JINTFP
Version: 0.1.1
Summary: Python package for creating node-based function pipeline.
Home-page: https://github.com/grasshopperTrainer/JINTFP
Author: grasshopperTrainer
Author-email: grasshoppertrainer@gmail.com
License: UNKNOWN
Keywords: function pipeline,functional pipeline,pipeline
Platform: UNKNOWN
Classifier: Development Status :: 3 - Alpha
Classifier: License :: OSI Approved :: MIT License
Classifier: Operating System :: OS Independent
Requires-Python: >=3
